COPYING
ChangeLog
MANIFEST.in
README.md
setup.py
python/diskhash/__init__.py
python/diskhash/_diskhash.c
python/diskhash/diskhash_version.py
python/diskhash/str2int_tool.py
python/diskhash.egg-info/PKG-INFO
python/diskhash.egg-info/SOURCES.txt
python/diskhash.egg-info/dependency_links.txt
python/diskhash.egg-info/top_level.txt
python/diskhash/tests/__init__.py
python/diskhash/tests/test_larger.py
python/diskhash/tests/test_smoke.py
src/diskhash.c
src/diskhash.h
src/primes.h
src/rtable.h