Metadata-Version: 2.1
Name: diskhash
Version: 0.4.1
Summary: Disk-based hashtable
Home-page: https://github.com/luispedro/diskhash
Author: Luis Pedro Coelho
Author-email: luis@luispedro.org
License: MIT
Platform: Any
Classifier: Intended Audience :: Developers
Classifier: Topic :: Software Development :: Libraries
Classifier: Programming Language :: Python
Classifier: Programming Language :: Python :: 2
Classifier: Programming Language :: Python :: 2.7
Classifier: Programming Language :: Python :: 3
Classifier: Programming Language :: Python :: 3.3
Classifier: Programming Language :: Python :: 3.4
Classifier: Programming Language :: Python :: 3.5
Classifier: Programming Language :: Python :: 3.6
Classifier: Programming Language :: Python :: 3.7
Classifier: Operating System :: OS Independent
Classifier: License :: OSI Approved :: MIT License
